mcp_get_weather/__init__.py
mcp_get_weather/__main__.py
mcp_get_weather/server.py
mcp_get_weather_bybowen-0.2.0.dist-info/METADATA
mcp_get_weather_bybowen-0.2.0.dist-info/WHEEL
mcp_get_weather_bybowen-0.2.0.dist-info/entry_points.txt
mcp_get_weather_bybowen-0.2.0.dist-info/top_level.txt
mcp_get_weather_bybowen-0.2.0.dist-info/RECORD
